{
  "n_rows": 1596,
  "predictors_present": [
    "ahlmann_bilinear_ridge",
    "biolord",
    "cpa",
    "gears_uncertainty",
    "mean",
    "noisy_mean",
    "scgen",
    "svaeplus"
  ],
  "datasets_present": [
    "adamson",
    "norman",
    "replogle_k562",
    "replogle_rpe1",
    "tahoe"
  ],
  "H1_capacity_hypothesis": {
    "hypothesis": "H1",
    "alternative": "greater",
    "n_datasets_tested": 5,
    "n_datasets_passing_threshold": 1,
    "preregistered_success_at_least_3_of_4": false,
    "per_dataset": {
      "adamson": {
        "rho": -0.22754898976351917,
        "p_value": 0.7165283471652835,
        "n_predictors": 8,
        "passes_preregistered_threshold": false
      },
      "norman": {
        "rho": 0.3832404038122429,
        "p_value": 0.1743825617438256,
        "n_predictors": 8,
        "passes_preregistered_threshold": false
      },
      "replogle_k562": {
        "rho": -0.26347777762091695,
        "p_value": 0.7501249875012499,
        "n_predictors": 8,
        "passes_preregistered_threshold": false
      },
      "replogle_rpe1": {
        "rho": 0.7228915662650601,
        "p_value": 0.023997600239976002,
        "n_predictors": 8,
        "passes_preregistered_threshold": true
      },
      "tahoe": {
        "rho": 0.5585812268712466,
        "p_value": 0.10548945105489452,
        "n_predictors": 7,
        "passes_preregistered_threshold": false
      }
    }
  },
  "H1b_data_hypothesis_per_dataset": {
    "hypothesis": "H1b",
    "alternative": "less",
    "n_datasets_tested": 5,
    "n_datasets_passing_threshold": 0,
    "preregistered_success_at_least_3_of_4": false,
    "per_dataset": {
      "adamson": {
        "rho": NaN,
        "p_value": 9.999000099990002e-05,
        "n_predictors": 8,
        "passes_preregistered_threshold": false
      },
      "norman": {
        "rho": NaN,
        "p_value": 9.999000099990002e-05,
        "n_predictors": 8,
        "passes_preregistered_threshold": false
      },
      "replogle_k562": {
        "rho": NaN,
        "p_value": 9.999000099990002e-05,
        "n_predictors": 8,
        "passes_preregistered_threshold": false
      },
      "replogle_rpe1": {
        "rho": NaN,
        "p_value": 9.999000099990002e-05,
        "n_predictors": 8,
        "passes_preregistered_threshold": false
      },
      "tahoe": {
        "rho": NaN,
        "p_value": 9.999000099990002e-05,
        "n_predictors": 7,
        "passes_preregistered_threshold": false
      }
    }
  },
  "H1b_data_hypothesis_cross_dataset": {
    "hypothesis": "H1b_cross_dataset",
    "rho": -0.39999999999999997,
    "p_value": 0.25807419258074193,
    "n_datasets": 5,
    "passes_preregistered_threshold": false
  },
  "preregistration_commit": "c7046e4b4c08106acd52c37e7ea8410e126d2ae4"
}