{
  "predictor": "ahlmann_bilinear_ridge",
  "noise_variant": "C_per_gene_marginal",
  "seed": 42,
  "n_common_perts": 35,
  "n_genes": 92,
  "weight_ess": 25.176666017001075,
  "per_score": {
    "ks": {
      "alpha_0.05": {
        "target": 0.95,
        "unweighted_coverage": 0.0,
        "weighted_coverage": 0.0,
        "unweighted_dev": 0.95,
        "weighted_dev": 0.95,
        "tau_unweighted": 0.371244,
        "tau_weighted": 0.371244
      },
      "alpha_0.1": {
        "target": 0.9,
        "unweighted_coverage": 0.0,
        "weighted_coverage": 0.0,
        "unweighted_dev": 0.9,
        "weighted_dev": 0.9,
        "tau_unweighted": 0.356431,
        "tau_weighted": 0.371244
      },
      "alpha_0.2": {
        "target": 0.8,
        "unweighted_coverage": 0.0,
        "weighted_coverage": 0.0,
        "unweighted_dev": 0.8,
        "weighted_dev": 0.8,
        "tau_unweighted": 0.336522,
        "tau_weighted": 0.371244
      }
    },
    "w1": {
      "alpha_0.05": {
        "target": 0.95,
        "unweighted_coverage": 0.0,
        "weighted_coverage": 0.0,
        "unweighted_dev": 0.95,
        "weighted_dev": 0.95,
        "tau_unweighted": 0.229824,
        "tau_weighted": 0.229824
      },
      "alpha_0.1": {
        "target": 0.9,
        "unweighted_coverage": 0.0,
        "weighted_coverage": 0.0,
        "unweighted_dev": 0.9,
        "weighted_dev": 0.9,
        "tau_unweighted": 0.196273,
        "tau_weighted": 0.229824
      },
      "alpha_0.2": {
        "target": 0.8,
        "unweighted_coverage": 0.0,
        "weighted_coverage": 0.0,
        "unweighted_dev": 0.8,
        "weighted_dev": 0.8,
        "tau_unweighted": 0.187453,
        "tau_weighted": 0.229824
      }
    },
    "energy": {
      "alpha_0.05": {
        "target": 0.95,
        "unweighted_coverage": 0.0,
        "weighted_coverage": 0.0,
        "unweighted_dev": 0.95,
        "weighted_dev": 0.95,
        "tau_unweighted": 0.283495,
        "tau_weighted": 0.283495
      },
      "alpha_0.1": {
        "target": 0.9,
        "unweighted_coverage": 0.0,
        "weighted_coverage": 0.0,
        "unweighted_dev": 0.9,
        "weighted_dev": 0.9,
        "tau_unweighted": 0.251587,
        "tau_weighted": 0.283495
      },
      "alpha_0.2": {
        "target": 0.8,
        "unweighted_coverage": 0.0,
        "weighted_coverage": 0.0,
        "unweighted_dev": 0.8,
        "weighted_dev": 0.8,
        "tau_unweighted": 0.239648,
        "tau_weighted": 0.283495
      }
    },
    "mmd_rbf": {
      "alpha_0.05": {
        "target": 0.95,
        "unweighted_coverage": 0.0,
        "weighted_coverage": 0.0,
        "unweighted_dev": 0.95,
        "weighted_dev": 0.95,
        "tau_unweighted": 0.022813,
        "tau_weighted": 0.022813
      },
      "alpha_0.1": {
        "target": 0.9,
        "unweighted_coverage": 0.0,
        "weighted_coverage": 0.0,
        "unweighted_dev": 0.9,
        "weighted_dev": 0.9,
        "tau_unweighted": 0.014292,
        "tau_weighted": 0.022813
      },
      "alpha_0.2": {
        "target": 0.8,
        "unweighted_coverage": 0.0,
        "weighted_coverage": 0.0,
        "unweighted_dev": 0.8,
        "weighted_dev": 0.8,
        "tau_unweighted": 0.008363,
        "tau_weighted": 0.009388
      }
    },
    "bimodality_mismatch": {
      "alpha_0.05": {
        "target": 0.95,
        "unweighted_coverage": 0.8571,
        "weighted_coverage": 0.8571,
        "unweighted_dev": 0.0929,
        "weighted_dev": 0.0929,
        "tau_unweighted": 0.771739,
        "tau_weighted": 0.771739
      },
      "alpha_0.1": {
        "target": 0.9,
        "unweighted_coverage": 0.2286,
        "weighted_coverage": 0.8571,
        "unweighted_dev": 0.6714,
        "weighted_dev": 0.0429,
        "tau_unweighted": 0.695652,
        "tau_weighted": 0.771739
      },
      "alpha_0.2": {
        "target": 0.8,
        "unweighted_coverage": 0.0571,
        "weighted_coverage": 0.8571,
        "unweighted_dev": 0.7429,
        "weighted_dev": 0.0571,
        "tau_unweighted": 0.641304,
        "tau_weighted": 0.771739
      }
    },
    "variance_ratio_dev": {
      "alpha_0.05": {
        "target": 0.95,
        "unweighted_coverage": 0.0,
        "weighted_coverage": 0.0,
        "unweighted_dev": 0.95,
        "weighted_dev": 0.95,
        "tau_unweighted": 0.487274,
        "tau_weighted": 0.487274
      },
      "alpha_0.1": {
        "target": 0.9,
        "unweighted_coverage": 0.0,
        "weighted_coverage": 0.0,
        "unweighted_dev": 0.9,
        "weighted_dev": 0.9,
        "tau_unweighted": 0.347446,
        "tau_weighted": 0.487274
      },
      "alpha_0.2": {
        "target": 0.8,
        "unweighted_coverage": 0.0,
        "weighted_coverage": 0.0,
        "unweighted_dev": 0.8,
        "weighted_dev": 0.8,
        "tau_unweighted": 0.312936,
        "tau_weighted": 0.316528
      }
    }
  },
  "elapsed_sec": 353.0
}